pytest_ext/__init__.py
pytest_ext/plugin.py
pytest_ext/config/__init__.py
pytest_ext/config/default_settings.py
pytest_ext/libs/__init__.py
pytest_ext/libs/helper.py
pytest_ext/ui_libs/__init__.py
pytest_ext/ui_libs/base_page.py
pytest_ext/ui_libs/basicelement.py
pytest_ext/ui_libs/element_ext.py
pytest_ext-1.0.1.dist-info/METADATA
pytest_ext-1.0.1.dist-info/WHEEL
pytest_ext-1.0.1.dist-info/entry_points.txt
pytest_ext-1.0.1.dist-info/top_level.txt
pytest_ext-1.0.1.dist-info/RECORD
