Metadata-Version: 2.1
Name: pytest-ext
Version: 1.0.1
Summary: pytest plugin for automation test
Home-page: https://github.com/mrene327/pytest-ext
Author: Wenlong Chen
Author-email: mrene327@gmail.com
License: MIT
Classifier: License :: OSI Approved :: MIT License
Classifier: Operating System :: OS Independent
Classifier: Programming Language :: Python :: 3 :: Only
Requires-Python: >=3.6
Requires-Dist: pytest >=5.3
Requires-Dist: allure-pytest >=2.8
Requires-Dist: pyyaml >=5.3.1
Requires-Dist: grocery >=1.4.0
